sentence_generalized_pooling/__init__.py
sentence_generalized_pooling/generalized_sentence_transformer_maker.py
sentence_generalized_pooling/multihead_generalized_pooling.py
sentence_generalized_pooling-0.9.0.dist-info/METADATA
sentence_generalized_pooling-0.9.0.dist-info/WHEEL
sentence_generalized_pooling-0.9.0.dist-info/top_level.txt
sentence_generalized_pooling-0.9.0.dist-info/RECORD
