Metadata-Version: 2.2
Name: sentence-generalized-pooling
Version: 0.9.0
Summary: A library implementing generalized pooling for sentence transformers
Home-page: https://github.com/RomainDarous/sentence-generalized-pooling
Author: Romain Darous
Author-email: romain.darous@telecom-paris.fr
License: MIT
Classifier: Programming Language :: Python :: 3
Classifier: License :: OSI Approved :: MIT License
Classifier: Operating System :: OS Independent
Requires-Python: >=3.6
Requires-Dist: torch>=1.7.0
Requires-Dist: sentence-transformers>=2.0.0
Dynamic: author
Dynamic: author-email
Dynamic: classifier
Dynamic: description
Dynamic: description-content-type
Dynamic: home-page
Dynamic: license
Dynamic: requires-dist
Dynamic: requires-python
Dynamic: summary
